dawnai/__init__.py
dawnai/config.py
dawnai/strategy/__init__.py
dawnai/strategy/base.py
dawnai/strategy/engine.py
dawnai/strategy/functions.py
dawnai/strategy/triggers.py
dawnai_strategy_sdk-0.1.0.dist-info/METADATA
dawnai_strategy_sdk-0.1.0.dist-info/WHEEL
dawnai_strategy_sdk-0.1.0.dist-info/RECORD
