Metadata-Version: 2.4
Name: dawnai-strategy-sdk
Version: 0.1.0
Summary: DawnAI Strategy SDK for efficient strategy development
Requires-Python: >=3.13
Requires-Dist: httpx>=0.25.0
Requires-Dist: pydantic>=2.5.0
Requires-Dist: python-dateutil>=2.8.2
Requires-Dist: typing-extensions>=4.9.0
Provides-Extra: dev
Requires-Dist: black==25.1.0; extra == 'dev'
Requires-Dist: mypy==1.17.1; extra == 'dev'
Requires-Dist: pytest-asyncio>=0.21.0; extra == 'dev'
Requires-Dist: pytest>=7.4.0; extra == 'dev'
Requires-Dist: ruff==0.12.11; extra == 'dev'
